mini_toolbox/__init__.py
mini_toolbox/api_json.py
mini_toolbox/archive.py
mini_toolbox/config.py
mini_toolbox/crypt.py
mini_toolbox/dingtalk.py
mini_toolbox/extra.py
mini_toolbox/ftp.py
mini_toolbox/git.py
mini_toolbox/hash.py
mini_toolbox/jenkins.py
mini_toolbox/jfrog.py
mini_toolbox/logger.py
mini_toolbox/mail.py
mini_toolbox/mysql.py
mini_toolbox/path.py
mini_toolbox/pip_list.py
mini_toolbox/recoding.py
mini_toolbox/ssh.py
mini_toolbox/svn.py
mini_toolbox/utils.py
mini_toolbox/xlsx.py
mini_toolbox/xml.py
mini_toolbox/alpha/__init__.py
mini_toolbox/alpha/mini_server.py
mini_toolbox/useless/__init__.py
mini_toolbox-1.1.0.dist-info/METADATA
mini_toolbox-1.1.0.dist-info/WHEEL
mini_toolbox-1.1.0.dist-info/entry_points.txt
mini_toolbox-1.1.0.dist-info/license_files/LICENSE
mini_toolbox-1.1.0.dist-info/RECORD
