Metadata-Version: 2.1
Name: mini-toolbox
Version: 1.1.0
Summary: Python迷你工具箱，包含简化的常用工具，旨在帮助脚本快速开发。
Project-URL: Changelog, https://mini-toolbox.readthedocs.io/latest/CHANGELOG.html
Project-URL: Documentation, https://mini-toolbox.readthedocs.io
Project-URL: Homepage, https://pypi.org/project/mini-toolbox
Project-URL: Issues, https://github.com/gnzhoutian/mini_toolbox/issues
Project-URL: Repository, https://github.com/gnzhoutian/mini_toolbox.git
Author-email: gnzhoutian <gnzhoutian@qq.com>
Keywords: mini-toolbox,mini-tools,toolbox,tools
Classifier: Development Status :: 4 - Beta
Classifier: Intended Audience :: Developers
Classifier: License :: OSI Approved :: MIT License
Classifier: Natural Language :: Chinese (Simplified)
Classifier: Operating System :: OS Independent
Classifier: Programming Language :: Python :: 3 :: Only
Classifier: Programming Language :: Python :: 3.6
Classifier: Topic :: Documentation :: Sphinx
Classifier: Topic :: Software Development :: Libraries :: Python Modules
Requires-Python: >=3.6
Provides-Extra: build
Requires-Dist: build; extra == 'build'
Requires-Dist: pytest; extra == 'build'
Requires-Dist: twine; extra == 'build'
Requires-Dist: virtualenv; extra == 'build'
Provides-Extra: docs
Requires-Dist: myst-parser==0.16.1; extra == 'docs'
Requires-Dist: sphinx-rtd-theme==1.1.1; extra == 'docs'
Requires-Dist: sphinx==4.5.0; extra == 'docs'
Provides-Extra: full
Requires-Dist: apscheduler; extra == 'full'
Requires-Dist: beautifulsoup4; extra == 'full'
Requires-Dist: charamel; extra == 'full'
Requires-Dist: colorlog; extra == 'full'
Requires-Dist: jenkinsapi; extra == 'full'
Requires-Dist: lxml; extra == 'full'
Requires-Dist: openpyxl; extra == 'full'
Requires-Dist: paramiko; extra == 'full'
Requires-Dist: pip>=19.0.0; extra == 'full'
Requires-Dist: pyartifactory>=1.11.0; extra == 'full'
Requires-Dist: pydes; extra == 'full'
Requires-Dist: pymysql; extra == 'full'
Requires-Dist: python-gitlab; extra == 'full'
Requires-Dist: requests>=2.20.0; extra == 'full'
Requires-Dist: rsa>=4.5; extra == 'full'
Requires-Dist: setuptools>=39.0.0; extra == 'full'
Requires-Dist: toml; extra == 'full'
Requires-Dist: wheel; extra == 'full'
Requires-Dist: xlrd==1.2.0; extra == 'full'
Requires-Dist: yapf; extra == 'full'
